cipdb/__init__.py
cipdb/__main__.py
cipdb/_core.py
cipdb-0.1.0.dist-info/licenses/LICENSE
cipdb-0.1.0.dist-info/METADATA
cipdb-0.1.0.dist-info/WHEEL
cipdb-0.1.0.dist-info/top_level.txt
cipdb-0.1.0.dist-info/RECORD
