Metadata-Version: 2.4
Name: cipdb
Version: 0.1.0
Summary: Conditional iPDB - Simple conditional debugging for Python
Author-email: ywatanabe <Yusuke.Watanabe@scitex.ai>
Maintainer-email: ywatanabe <Yusuke.Watanabe@scitex.ai>
License: MIT
Project-URL: Homepage, https://github.com/ywatanabe/cipdb
Project-URL: Repository, https://github.com/ywatanabe/cipdb
Project-URL: Documentation, https://github.com/ywatanabe/cipdb
Project-URL: Issues, https://github.com/ywatanabe/cipdb/issues
Keywords: debugging,ipdb,pdb,conditional,breakpoint
Classifier: Development Status :: 4 - Beta
Classifier: Intended Audience :: Developers
Classifier: License :: OSI Approved :: MIT License
Classifier: Operating System :: OS Independent
Classifier: Programming Language :: Python :: 3
Classifier: Programming Language :: Python :: 3.6
Classifier: Programming Language :: Python :: 3.7
Classifier: Programming Language :: Python :: 3.8
Classifier: Programming Language :: Python :: 3.9
Classifier: Programming Language :: Python :: 3.10
Classifier: Programming Language :: Python :: 3.11
Classifier: Programming Language :: Python :: 3.12
Classifier: Topic :: Software Development :: Debuggers
Requires-Python: >=3.6
License-File: LICENSE
Requires-Dist: ipdb>=0.13.0
Provides-Extra: dev
Requires-Dist: pytest>=6.0.0; extra == "dev"
Requires-Dist: pytest-cov>=2.10.0; extra == "dev"
Requires-Dist: pytest-testmon>=2.0.0; extra == "dev"
Requires-Dist: ruff>=0.7.0; extra == "dev"
Requires-Dist: mypy>=1.0.0; extra == "dev"
Requires-Dist: build>=0.10.0; extra == "dev"
Requires-Dist: twine>=4.0.0; extra == "dev"
Dynamic: license-file
